{"cameraMode":{"drawMode":0,"name":"Shaded","section":"Shading Mode"},"sceneLighting":false,"audioPlay":false,"sceneViewState":{"m_AlwaysRefresh":false,"showFog":true,"showSkybox":false,"showFlares":true,"showImageEffects":true,"showParticleSystems":true,"showVisualEffectGraphs":true,"m_FxEnabled":true},"in2DMode":false,"pivot":{"x":0.8715305328369141,"y":-0.44442129135131838,"z":1.9534834623336793},"rotation":{"x":-0.21338684856891633,"y":-0.44050338864326479,"z":0.1086851954460144,"w":-0.8652790784835815},"size":0.7004019021987915,"orthographic":false}